ipyprogressivis/MANIFEST.in
ipyprogressivis/__init__.py
ipyprogressivis/_frontend.py
ipyprogressivis/_version.py
ipyprogressivis/app.py
ipyprogressivis/hook_tools.py
ipyprogressivis/install.json
ipyprogressivis/jupyter-progressivis.json
ipyprogressivis/magics.py
ipyprogressivis/pre_save.py
ipyprogressivis/pre_save_md.py
ipyprogressivis/pre_save_x.py
ipyprogressivis/py.typed
ipyprogressivis/js/.babelrc
ipyprogressivis/js/.eslintrc.js
ipyprogressivis/js/README.md
ipyprogressivis/js/package.json
ipyprogressivis/js/webpack.config.js
ipyprogressivis/js/yarn.lock
ipyprogressivis/js/css/main.css
ipyprogressivis/js/css/module-graph.css
ipyprogressivis/js/css/scatterplot.css
ipyprogressivis/js/css/sparkline-progressbar.css
ipyprogressivis/js/lib/.gitkeep
ipyprogressivis/js/lib/backup.js
ipyprogressivis/js/lib/base.js
ipyprogressivis/js/lib/cell_out.js
ipyprogressivis/js/lib/colormaps.js
ipyprogressivis/js/lib/commands.js
ipyprogressivis/js/lib/config-editor.js
ipyprogressivis/js/lib/dag_widget.js
ipyprogressivis/js/lib/data_table.js
ipyprogressivis/js/lib/embed.js
ipyprogressivis/js/lib/es6-element-ready.js
ipyprogressivis/js/lib/extension.js
ipyprogressivis/js/lib/functions.js
ipyprogressivis/js/lib/history.js
ipyprogressivis/js/lib/index.js
ipyprogressivis/js/lib/json_editor.js
ipyprogressivis/js/lib/json_html.js
ipyprogressivis/js/lib/labplugin.js
ipyprogressivis/js/lib/line_graph.js
ipyprogressivis/js/lib/module_graph.js
ipyprogressivis/js/lib/previmages.js
ipyprogressivis/js/lib/scatterplot.js
ipyprogressivis/js/lib/sensitive_html.js
ipyprogressivis/js/lib/sparkline_progressbar.js
ipyprogressivis/js/lib/talker.js
ipyprogressivis/js/schema/plugin.json
ipyprogressivis/js/src/backup.js
ipyprogressivis/js/src/base.js
ipyprogressivis/js/src/cell_out.js
ipyprogressivis/js/src/colormaps.js
ipyprogressivis/js/src/commands.js
ipyprogressivis/js/src/config-editor.jsx
ipyprogressivis/js/src/dag_widget.js
ipyprogressivis/js/src/data_table.js
ipyprogressivis/js/src/embed.js
ipyprogressivis-0.3.0.dist-info/METADATA
ipyprogressivis-0.3.0.dist-info/WHEEL
ipyprogressivis-0.3.0.dist-info/licenses/LICENSE
ipyprogressivis-0.3.0.dist-info/RECORD
