Metadata-Version: 2.4
Name: ipyprogressivis
Version: 0.3.0
Summary: A Custom Jupyter Widget Library for Progressivis
Project-URL: Homepage, https://github.com/progressivis/ipyprogressivis
Author-email: "INRIA, Jean-Daniel Fekete, Christian Poli" <jean-daniel.fekete@inria.fr>
License-Expression: BSD-2-Clause
License-File: LICENSE
Keywords: IPython,Jupyter,Widgets
Classifier: Framework :: Jupyter
Classifier: Framework :: Jupyter :: JupyterLab
Classifier: Framework :: Jupyter :: JupyterLab :: 4
Classifier: Framework :: Jupyter :: JupyterLab :: Extensions
Classifier: Framework :: Jupyter :: JupyterLab :: Extensions :: Prebuilt
Classifier: Intended Audience :: Developers
Classifier: Intended Audience :: Science/Research
Classifier: License :: OSI Approved :: BSD License
Classifier: Programming Language :: Python
Classifier: Programming Language :: Python :: 3
Classifier: Programming Language :: Python :: 3.10
Classifier: Programming Language :: Python :: 3.11
Classifier: Programming Language :: Python :: 3.12
Classifier: Programming Language :: Python :: 3.13
Requires-Python: >=3.10
Requires-Dist: ipydatawidgets
Requires-Dist: ipywidgets<9,>=7.6
Requires-Dist: jupyter-client>=8.6.0
Requires-Dist: lz4
Requires-Dist: numpy>=1.26.4
Requires-Dist: pandas<3.0.0,>=1.0.0
Requires-Dist: pillow
Requires-Dist: sidecar>=0.7.0
Requires-Dist: traitlets>=4.3.0
Requires-Dist: traittypes>=0.0.6
Requires-Dist: vega>=4.0.0
Provides-Extra: dev
Requires-Dist: jupyterlab>=4.0.0; extra == 'dev'
Provides-Extra: progressivis
Requires-Dist: progressivis; extra == 'progressivis'
Provides-Extra: test
Requires-Dist: nbval; extra == 'test'
Requires-Dist: pytest-cov; extra == 'test'
Requires-Dist: pytest>=6.0; extra == 'test'
Provides-Extra: typing
Requires-Dist: duckdb; extra == 'typing'
Requires-Dist: ipython; extra == 'typing'
Requires-Dist: jinja2; extra == 'typing'
Requires-Dist: mypy>=1.0.1; extra == 'typing'
Requires-Dist: numpy; extra == 'typing'
Requires-Dist: pandas-stubs; extra == 'typing'
Requires-Dist: sqlalchemy-stubs; extra == 'typing'
Requires-Dist: traits-stubs; extra == 'typing'
Requires-Dist: traittypes; extra == 'typing'
Requires-Dist: typeguard; extra == 'typing'
Requires-Dist: types-pillow; extra == 'typing'
Requires-Dist: types-pytz; extra == 'typing'
Requires-Dist: types-pyyaml; extra == 'typing'
Requires-Dist: types-requests; extra == 'typing'
Requires-Dist: types-setuptools; extra == 'typing'
Requires-Dist: types-urllib3; extra == 'typing'
Requires-Dist: typing-extensions; extra == 'typing'
